AeroTechAPI.py
utils.py
AeroTechAPI-1.0.0.dist-info/LICENSE.txt
AeroTechAPI-1.0.0.dist-info/METADATA
AeroTechAPI-1.0.0.dist-info/WHEEL
AeroTechAPI-1.0.0.dist-info/top_level.txt
AeroTechAPI-1.0.0.dist-info/RECORD
