Metadata-Version: 2.1
Name: AeroTechAPI
Version: 1.0.0
Summary: API for the Aerotech A3200 controller
Home-page: UNKNOWN
Author: Frederic Schell
Author-email: frederic.jschell@gmail.com
License: UNKNOWN
Platform: UNKNOWN
Classifier: Programming Language :: Python :: 3
Classifier: Programming Language :: Python :: 3.6
Classifier: Programming Language :: Python :: 3.7
Classifier: Programming Language :: Python :: 3.8
Classifier: Programming Language :: Python :: 3.9
Classifier: License :: OSI Approved :: MIT License
Requires-Python: >=3.6
